maxml/__init__.py
maxml/version.txt
maxml/element/__init__.py
maxml/enumerations/__init__.py
maxml/exceptions/__init__.py
maxml/logging/__init__.py
maxml/namespace/__init__.py
maxml-1.0.4.dist-info/METADATA
maxml-1.0.4.dist-info/WHEEL
maxml-1.0.4.dist-info/top_level.txt
maxml-1.0.4.dist-info/zip-safe
maxml-1.0.4.dist-info/RECORD
