Metadata-Version: 2.4
Name: maxml
Version: 1.0.4
Summary: A streamlined pure Python XML serializer.
Author: Daniel Sissman
License-Expression: MIT
Project-URL: documentation, https://github.com/bluebinary/maxml/blob/main/README.md
Project-URL: changelog, https://github.com/bluebinary/maxml/blob/main/CHANGELOG.md
Project-URL: repository, https://github.com/bluebinary/maxml
Project-URL: issues, https://github.com/bluebinary/maxml/issues
Project-URL: homepage, https://github.com/bluebinary/maxml
Keywords: xml,serialization,xml serialization,xml writer
Platform: any
Classifier: Programming Language :: Python :: 3
Classifier: Programming Language :: Python :: 3.10
Classifier: Programming Language :: Python :: 3.11
Classifier: Programming Language :: Python :: 3.12
Classifier: Programming Language :: Python :: 3.13
Requires-Python: >=3.10
Requires-Dist: classicist==1.0.*
Requires-Dist: enumerific==1.0.*
Provides-Extra: development
Requires-Dist: black==24.10.*; extra == "development"
Requires-Dist: pytest==8.3.*; extra == "development"
Requires-Dist: pytest-codeblocks==0.17.0; extra == "development"
Provides-Extra: distribution
Requires-Dist: build; extra == "distribution"
Requires-Dist: twine; extra == "distribution"
Requires-Dist: wheel; extra == "distribution"
